LICENSE
MANIFEST.in
README.rst
pyproject.toml
setup.py
kdcount/__init__.py
kdcount/bootstrap.py
kdcount/cluster.py
kdcount/correlate.py
kdcount/kd_count.c
kdcount/kd_enum.c
kdcount/kd_fof.c
kdcount/kd_fof_linkedlist.c
kdcount/kd_force.c
kdcount/kd_grav.h
kdcount/kd_integrate.c
kdcount/kdtree.c
kdcount/kdtree.h
kdcount/models.py
kdcount/pykdcount.c
kdcount/pykdcount.pyx
kdcount/sphere.py
kdcount/utils.py
kdcount/version.py
kdcount.egg-info/PKG-INFO
kdcount.egg-info/SOURCES.txt
kdcount.egg-info/dependency_links.txt
kdcount.egg-info/not-zip-safe
kdcount.egg-info/top_level.txt
kdcount/tests/__init__.py
kdcount/tests/test_bootstrap.py
kdcount/tests/test_cluster.py
kdcount/tests/test_correlate.py
kdcount/tests/test_model.py
kdcount/tests/test_sphere.py
kdcount/tests/test_tree.py